pyqube/__init__.py
pyqube/events/__init__.py
pyqube/events/clients.py
pyqube/events/exceptions.py
pyqube/events/handlers.py
pyqube/events/tests/__init__.py
pyqube/events/tests/test_mqtt_client.py
pyqube/events/tests/test_mqtt_event_handler_base.py
pyqube/events/tests/test_queue_handler.py
pyqube/events/tests/test_queue_handler_decorator.py
pyqube/events/tests/test_queuing_system_reset_decorator.py
pyqube/events/tests/test_queuing_system_reset_handler.py
pyqube/events/tests/test_ticket_handler.py
pyqube/events/tests/test_ticket_handler_decorator.py
pyqube/rest/__init__.py
pyqube/rest/clients.py
pyqube/rest/exceptions.py
pyqube/rest/graphql_generators.py
pyqube/rest/queue_management_manager.py
pyqube/rest/tests/__init__.py
pyqube/rest/tests/test_call_next_ticket_ending_current.py
pyqube/rest/tests/test_end_answering.py
pyqube/rest/tests/test_generate_ticket.py
pyqube/rest/tests/test_get_current_answering.py
pyqube/rest/tests/test_list_queues.py
pyqube/rest/tests/test_list_queues_of_queues_list.py
pyqube/rest/tests/test_rest_client.py
pyqube/rest/tests/test_set_current_counter.py
pyqube/rest/tests/test_set_queue_status.py
pyqube/types.py
pyqube-0.3.2.dist-info/LICENSE
pyqube-0.3.2.dist-info/METADATA
pyqube-0.3.2.dist-info/WHEEL
pyqube-0.3.2.dist-info/RECORD
