Metadata-Version: 2.3
Name: pyqube
Version: 0.3.2
Summary: A Python SDK for interacting with the qube REST API and subscribing to real-time events
License: MIT
Author: q-better
Author-email: dev@q-better.com
Requires-Python: >=3.11,<4.0
Classifier: License :: OSI Approved :: MIT License
Classifier: Programming Language :: Python :: 3
Classifier: Programming Language :: Python :: 3.11
Classifier: Programming Language :: Python :: 3.12
Classifier: Programming Language :: Python :: 3.13
Requires-Dist: paho-mqtt (>=2.1.0,<3.0.0)
Requires-Dist: requests (>=2.32.3,<3.0.0)
Project-URL: Documentation, https://docs.qube.q-better.com/docs/guides/getting-started
Project-URL: Issue Tracker, https://github.com/Q-Better/pyqube/issues
Project-URL: Repository, https://github.com/Q-Better/pyqube
